banner_rlaehgus97/__init__.py
banner_rlaehgus97/banner.py
banner_rlaehgus97-0.3.1.dist-info/METADATA
banner_rlaehgus97-0.3.1.dist-info/WHEEL
banner_rlaehgus97-0.3.1.dist-info/entry_points.txt
banner_rlaehgus97-0.3.1.dist-info/top_level.txt
banner_rlaehgus97-0.3.1.dist-info/RECORD
