Metadata-Version: 2.1
Name: banner_rlaehgus97
Version: 0.3.1
Summary: Banner Output Program
Author-email: rlaehgus97 <starkim625@gmail.com>
License: MIT
Project-URL: Homepage, https://github.com/rlaehgus97/banner_rlaehgus97
Project-URL: Issues, https://github.com/rlaehgus97/banner_rlaehgus97/issues
Requires-Python: >=3.9
Requires-Dist: pyfiglet >=1.0.2
